yta_video_editor/__init__.py
yta_video_editor/change/__init__.py
yta_video_editor/change/position/__init__.py
yta_video_editor/change/position/absolute.py
yta_video_editor/change/position/offset.py
yta_video_editor/change/resize/__init__.py
yta_video_editor/change/resize/absolute.py
yta_video_editor/change/resize/offset.py
yta_video_editor/change/rotation/__init__.py
yta_video_editor/change/rotation/absolute.py
yta_video_editor/change/rotation/offset.py
yta_video_editor/change/transform/__init__.py
yta_video_editor/change/transform/color.py
yta_video_editor/parameter/__init__.py
yta_video_editor/settings.py
yta_video_editor/to_remove/__init__.py
yta_video_editor/to_remove/editor.py
yta_video_editor/to_remove/modifications/__init__.py
yta_video_editor/to_remove/modifications/color_temperature_video_modification.py
yta_video_editor/to_remove/modifications/video_modification.py
yta_video_editor/to_remove/modifications/video_modifications.py
yta_video_editor/to_remove/video/__init__.py
yta_video_editor/to_remove/video/attribute.py
yta_video_editor/to_remove/video/attribute_modifier.py
yta_video_editor/utils.py
yta_video_editor-0.1.31.dist-info/licenses/LICENSE
yta_video_editor-0.1.31.dist-info/METADATA
yta_video_editor-0.1.31.dist-info/WHEEL
yta_video_editor-0.1.31.dist-info/RECORD
